tmpack/__init__.py
tmpack-0.0.0.dist-info/METADATA
tmpack-0.0.0.dist-info/WHEEL
tmpack-0.0.0.dist-info/top_level.txt
tmpack-0.0.0.dist-info/RECORD
