Metadata-Version: 2.1
Name: tmpack
Version: 0.0.0
Summary: Coming soon
Author-email: tspt2479@gmail.com
